spatial3d/__init__.py
spatial3d/aabb.py
spatial3d/coordinate_axes.py
spatial3d/dual.py
spatial3d/edge.py
spatial3d/euler/__init__.py
spatial3d/euler/axes.py
spatial3d/euler/order.py
spatial3d/exceptions.py
spatial3d/facet.py
spatial3d/intersection.py
spatial3d/kdtree.py
spatial3d/matrix4.py
spatial3d/mesh.py
spatial3d/parameters.py
spatial3d/py.typed
spatial3d/quaternion.py
spatial3d/ray.py
spatial3d/swizzler.py
spatial3d/transform.py
spatial3d/vector3.py
spatial3d-0.8.0.dist-info/LICENSE
spatial3d-0.8.0.dist-info/WHEEL
spatial3d-0.8.0.dist-info/METADATA
spatial3d-0.8.0.dist-info/RECORD
